jax_pep503/__init__.py
jax_pep503/build.py
jax_pep503/main.py
jax_pep503-0.4.2.dist-info/LICENSE
jax_pep503-0.4.2.dist-info/METADATA
jax_pep503-0.4.2.dist-info/WHEEL
jax_pep503-0.4.2.dist-info/entry_points.txt
jax_pep503-0.4.2.dist-info/RECORD
