Metadata-Version: 2.1
Name: jax-pep503
Version: 0.4.2
Summary: PEP 503 compliant repository for Jax
Home-page: https://jorenham.github.io/jax_pep503/
License: Apache-2.0
Author: Joren Hammudoglu
Author-email: jhammudoglu@gmail.com
Requires-Python: >=3.10,<4.0
Classifier: License :: OSI Approved :: Apache Software License
Classifier: Programming Language :: Python :: 3
Classifier: Programming Language :: Python :: 3.10
Classifier: Programming Language :: Python :: 3.11
Requires-Dist: Jinja2 (>=3.1,<4.0)
Requires-Dist: aioboto3 (>=11.3.0,<12.0.0)
Requires-Dist: fastapi (>=0.101,<1.0)
Requires-Dist: httpx (>=0.24,<1.0)
Requires-Dist: mainpy (>=1.1.0,<2.0.0)
Requires-Dist: uvicorn (>=0.23,<1.0)
Project-URL: GitHub, https://github.com/jorenham/jax_pep503
Project-URL: PEP 503 Repository, https://jorenham.github.io/jax_pep503/
Project-URL: Repository, https://github.com/jorenham/jax_pep503
